README.md
setup.cfg
setup.py
gym_plannable/__init__.py
gym_plannable/agent.py
gym_plannable/common.py
gym_plannable/multi_agent.py
gym_plannable/plannable.py
gym_plannable/score_tracker.py
gym_plannable.egg-info/PKG-INFO
gym_plannable.egg-info/SOURCES.txt
gym_plannable.egg-info/dependency_links.txt
gym_plannable.egg-info/not-zip-safe
gym_plannable.egg-info/requires.txt
gym_plannable.egg-info/top_level.txt
gym_plannable/env/__init__.py
gym_plannable/env/grid_world.py
gym_plannable/env/render.py
gym_plannable/env/tic_tac_toe.py
tests/__init__.py
tests/dummy_envs.py
tests/multi_agent_mixins.py
tests/plannable_mixins.py
tests/test_gridworld.py
tests/test_multi_agent.py
tests/test_plannable.py